Workbook

Sheet Plan d'action
A1: LA VIE FINANCIÈRE — plan d'action
A2: Acquisition des marques et des noms de domaine en nom propre. Édition confiée à MIKA via une société commerciale distincte. Situation au 20 août 2026.
A4: # | B4: Action | C4: Échéance | D4: Responsable | E4: Coût mini (€) | F4: Coût maxi (€) | G4: Statut | H4: Bloquant pour
A5: 1 | B5: Trancher la détention : seul, ou 50/50 avec Jonathan | C5: Immédiat | D5: FO | E5: 0 | F5: 0 | G5: À faire | H5: La fenêtre est ouverte tant que la marque ne vaut rien
A6: 2 | B6: Réserver laviefinanciere.fr, lesetoilesdelassurancevie.fr, lesetoilesdupatrimoine.fr | C6: Immédiat | D6: FO | E6: =Domaines!F23 -> 135 | F6: =Domaines!F23 -> 135 | G6: À faire | H6: Rien, mais à faire avant le dépôt (publication au BOPI)
A7: 3 | B7: Placer un backorder sur laviefinanciere.com | C7: Immédiat | D7: FO | E7: 30 | F7: 60 | G7: À faire | H7: Rien
A8: 4 | B8: Vérifier le régime matrimonial ; si bien propre voulu, financer sur des propres et documenter le remploi | C8: Immédiat | D8: FO | E8: 0 | F8: 0 | G8: À faire | H8: L'acquisition — ne se rattrape pas après
A9: 5 | B9: Mandater un CPI : recherche d'antériorités classes 16/35/41, France + MUE + Madrid | C9: Cette semaine | D9: FO | E9: 400 | F9: 900 | G9: À faire | H9: Le dépôt — seul point encore bloquant
A10: 6 | B10: Dépôt INPI : LA VIE FINANCIÈRE, verbale, classes 16, 35, 41 | C10: J+10 | D10: FO | E10: =Depots!E7 -> 270 | F10: =Depots!E7 -> 270 | G10: À faire | H10: —
A11: 7 | B11: Dépôt INPI : LES ÉTOILES DE L'ASSURANCE VIE, verbale, classes 35, 41 | C11: J+10 | D11: FO | E11: =Depots!E8 -> 230 | F11: =Depots!E8 -> 230 | G11: À faire | H11: —
A12: 8 | B12: Constituer le dossier de preuve de disponibilité (dossier de reprise, UDRP D2010-0529, archives) | C12: J+10 | D12: FO | E12: 0 | F12: 0 | G12: À faire | H12: Une défense éventuelle
A13: 9 | B13: Consultation déontologique écrite du Bâtonnier sur l'exploitation du média | C13: Avant la relance | D13: FO | E13: 0 | F13: 0 | G13: À faire | H13: La relance, pas le dépôt
A14: 10 | B14: Protocole de lancement signé avec MIKA, avant qu'il constitue sa société | C14: Avant la relance | D14: FO | E14: 0 | F14: 0 | G14: À faire | H14: La constitution de l'éditrice
A15: 11 | B15: Licence de marque signée en nom propre (redevance fixe, usage documenté, changement de contrôle) | C15: Avant la relance | D15: FO | E15: 0 | F15: 0 | G15: À faire | H15: L'exploitation
A16: 12 | B16: Décider si la marque reste en nom propre ou part en société — tant qu'elle ne vaut rien | C16: Avant la relance | D16: FO | E16: 0 | F16: 0 | G16: À faire | H16: La transmission et la fiscalité des flux
B17: TOTAL | E17: =SUM(E5:E16) -> 1065 | F17: =SUM(F5:F16) -> 1595
B19: Avancement (actions faites / total) | E19: =COUNTIF(G5:G16,"Fait")/COUNTA(G5:G16) -> 0
B20: Actions restantes | E20: =COUNTIF(G5:G16,"À faire")+COUNTIF(G5:G16,"En cours") -> 12

Sheet Depots
A1: Dépôts INPI
A2: Barème INPI : taxe de base pour une classe, puis un montant par classe supplémentaire. Les deux cellules jaunes sont les paramètres à ajuster si le barème change.
A4: Taxe de dépôt, 1 classe (€) | B4: 190
A5: Chaque classe supplémentaire (€) | B5: 40
A6: Marque | B6: Type | C6: Classes | D6: Nb de classes | E6: Coût (€) | F6: Statut | G6: Commentaire
A7: LA VIE FINANCIÈRE | B7: Verbale | C7: 16, 35, 41 | D7: 3 | E7: =IF(D7=0,0,$B$4+$B$5*(D7-1)) -> 270 | F7: À déposer | G7: Cœur du dispositif. Classe 36 seulement si le libellé reste étroit : information financière, sans conseil ni intermédiation.
A8: LES ÉTOILES DE L'ASSURANCE VIE | B8: Verbale | C8: 35, 41 | D8: 2 | E8: =IF(D8=0,0,$B$4+$B$5*(D8-1)) -> 230 | F8: À déposer | G8: Véhicule du palmarès annuel. À déposer en même temps que la priorité 1, pas après.
A9: LES ÉTOILES DU PATRIMOINE | B9: Verbale | C9: 35, 41 | D9: 2 | E9: =IF(D9=0,0,$B$4+$B$5*(D9-1)) -> 230 | F9: Optionnel | G9: Création nouvelle, sans historique de reprise. Utile si l'on veut un signe qui ne dépende d'aucune reprise.
A10: LA VIE FRANÇAISE | B10: — | C10: — | D10: 0 | E10: =IF(D10=0,0,$B$4+$B$5*(D10-1)) -> 0 | F10: Écarté | G10: Signe libre mais générique, et en zone de friction avec La Vie du groupe Bayard, toujours exploitée.
A11: TOTAL des dépôts marqués "À déposer" | E11: =SUMIF(F7:F10,"À déposer",E7:E10) -> 500
A13: Rappel : pas de classe 45 (services juridiques). Le média informe, le cabinet conseille, et les deux ne portent pas le même nom.
A14: Rappel : on ne dépose que les classes exploitées dans les cinq ans, le compteur de déchéance de l'art. L. 714-5 CPI partant de l'enregistrement.

Sheet Domaines
A1: Noms de domaine
A2: Statut établi par délégation DNS le 20/08/2026 avec scripts/check-domaines.py. « Libre » signifie non délégué, donc très probablement non enregistré : la confirmation se fait chez le registrar.
A4: Coût annuel unitaire estimé (€) | B4: 15
A6: Domaine | B6: Statut DNS (20/08/2026) | C6: Lecture | D6: Priorité | E6: Action | F6: Coût annuel (€)
A7: laviefinanciere.fr | B7: NXDOMAIN | C7: Libre | D7: 1 | E7: À réserver | F7: =IF($E7="À réserver",$B$4,0) -> 15
A8: lesetoilesdelassurancevie.fr | B8: NXDOMAIN | C8: Libre | D8: 1 | E8: À réserver | F8: =IF($E8="À réserver",$B$4,0) -> 15
A9: lesetoilesdupatrimoine.fr | B9: NXDOMAIN | C9: Libre | D9: 1 | E9: À réserver | F9: =IF($E9="À réserver",$B$4,0) -> 15
A10: lavie-financiere.fr | B10: NXDOMAIN | C10: Libre | D10: 2 | E10: À réserver | F10: =IF($E10="À réserver",$B$4,0) -> 15
A11: laviefinanciere.net | B11: NXDOMAIN | C11: Libre | D11: 2 | E11: À réserver | F11: =IF($E11="À réserver",$B$4,0) -> 15
A12: laviefinanciere.eu | B12: NXDOMAIN | C12: Libre | D12: 2 | E12: À réserver | F12: =IF($E12="À réserver",$B$4,0) -> 15
A13: lavie-financiere.com | B13: NXDOMAIN | C13: Libre | D13: 3 | E13: À réserver | F13: =IF($E13="À réserver",$B$4,0) -> 15
A14: lesetoilesdelassurancevie.com | B14: NXDOMAIN | C14: Libre | D14: 3 | E14: À réserver | F14: =IF($E14="À réserver",$B$4,0) -> 15
A15: lesetoilesdupatrimoine.com | B15: NXDOMAIN | C15: Libre | D15: 3 | E15: À réserver | F15: =IF($E15="À réserver",$B$4,0) -> 15
A16: etoilesdupatrimoine.fr | B16: NXDOMAIN | C16: Libre | D16: 3 | E16: Optionnel | F16: =IF($E16="À réserver",$B$4,0) -> 0
A17: etoiles-assurance-vie.fr | B17: NXDOMAIN | C17: Libre | D17: 3 | E17: Optionnel | F17: =IF($E17="À réserver",$B$4,0) -> 0
A18: viefinanciere.fr | B18: NXDOMAIN | C18: Libre | D18: 3 | E18: Optionnel | F18: =IF($E18="À réserver",$B$4,0) -> 0
... A22: laviefrancaise.com | B22: NOERROR | C22: Pris et résolu | D22: 3 | E22: Indisponible | F22: =IF($E22="À réserver",$B$4,0) -> 0
A23: TOTAL annuel des domaines à réserver | F23: =SUM(F7:F22) -> 135
A25: Titulaire : vous, en nom propre, avec vos coordonnées personnelles — jamais celles du cabinet. Un whois pointant vers BENSAID AVOCATS relierait publiquement le média au cabinet.
A26: Pour le .fr, l'AFNIC restreint par défaut la diffusion des données des personnes physiques. Pour .com, .net et .eu, activer la protection whois du registrar.

Sheet Budget
A1: Budget d'entrée
A2: Les lignes en vert sont calculées depuis les onglets Domaines et Depots. Les lignes en bleu sont des estimations à ajuster.
A4: Poste | B4: Mini (€) | C4: Maxi (€) | D4: Source
A5: Noms de domaine, première année | B5: =Domaines!F23 -> 135 | C5: =Domaines!F23 -> 135 | D5: Onglet Domaines, total des domaines à réserver
A6: Backorder sur laviefinanciere.com | B6: 30 | C6: 60 | D6: Estimation, tarif courant des prestataires de drop-catching
A7: Recherche d'antériorités complète par un CPI | B7: 400 | C7: 900 | D7: Fourchette de marché — couvre France, MUE et Madrid
A8: Dépôts INPI | B8: =Depots!E11 -> 500 | C8: =Depots!E11 -> 500 | D8: Onglet Depots, total des marques à déposer
A9: TOTAL À ENGAGER | B9: =SUM(B5:B8) -> 1065 | C9: =SUM(C5:C8) -> 1595
A11: Calendrier INPI : publication au BOPI sous six semaines, opposition deux mois, enregistrement en cinq à six mois sans opposition.
A12: Les droits rétroagissent à la date de dépôt : l'exploitation peut démarrer dès le dépôt, sous la mention ™ et non ®.

Sheet Portefeuille
A1: Portefeuille historique — toutes les marques sont expirées
A2: Source : données INPI et BODACC restituées par Pappers, vérifications du 19/08/2026. Les deux titulaires sont radiés : LA VIE FINANCIERE SA depuis le 25/04/2013, MONEYWEEK FRANCE depuis le 16/04/2015.
A4: N° INPI | B4: Signe | C4: Type | D4: Statut | E4: Expiration | F4: Classes
A5: FR99770603 | B5: LA VIE FINANCIERE | C5: Verbale | D5: Expirée | E5: 22/01/2019 | F5: 9, 16, 35, 36, 38, 41
A6: FR99785142 | B6: LA VIE FINANCIERE L'HEBDO CONSEIL DE VOTRE ARGENT | C6: Mixte | D6: Expirée | E6: 07/04/2019 | F6: 9, 16, 35, 36, 38, 41
A7: FR1463999 | B7: LA VIE FRANÇAISE | C7: Verbale | D7: Expirée | E7: 06/05/2018 | F7: 9, 16, 35, 36, 38, 39, 40, 41, 42
A8: FR3552878 | B8: LES ETOILES DE L'ASSURANCE VIE | C8: Verbale | D8: Expirée | E8: 01/02/2018 | F8: 35, 41
A9: FR3575774 | B9: LES ETOILES DE L'ASSURANCE VIE | C9: Mixte | D9: Expirée | E9: 15/05/2018 | F9: 35, 41
A10: FR3575798 | B10: LES ETOILES DE LA FINANCE | C10: Mixte | D10: Expirée | E10: 15/05/2018 | F10: 35, 41
A11: FR3575942 | B11: LES ETOILES DE L'IMMOBILIER | C11: Mixte | D11: Expirée | E11: 15/05/2018 | F11: 35, 41
A12: FR3575775 | B12: LES ETOILES DU LOGEMENT | C12: Mixte | D12: Expirée | E12: 15/05/2018 | F12: 35, 41
A13: FR3492526 | B13: L'IMMOBILIER + Net | C13: Mixte | D13: Expirée | E13: 03/04/2017 | F13: 36
A14: FR97708236 | B14: STRATEGIE GRAPHIQUE | C14: Verbale | D14: Expirée | E14: 10/12/2017 | F14: 36
A15: FR97681824 | B15: STRATEGIE GRAPHIQUE | C15: Verbale | D15: Expirée | E15: 10/06/2017 | F15: 9, 16, 38, 41
A17: À réconcilier : la décision UDRP OMPI D2010-0529 énumère trois marques « LA VIE FINANCIERE » enregistrées en 1999, là où ce relevé en recense deux sur ce signe. À trancher à l'INPI.

Sheet A trancher
A1: Points à trancher
A2: Colonnes Décision et Date à remplir. Une ligne d'exemple figure sur l'onglet Legende.
A4: # | B4: Point | C4: Échéance | D4: Décision | E4: Date
A5: 1 | B5: Détention : seul, ou 50/50 avec Jonathan. Si 50/50, le faire tant que la marque ne vaut rien | C5: Avant le dépôt
A6: 2 | B6: Régime matrimonial : bien commun ou bien propre, et financement en conséquence | C6: Avant l'acquisition
A7: 3 | B7: Marque en nom propre à titre durable, ou apport à une société civile | C7: Avant la relance
A8: 4 | B8: Classe 36 : déposée avec un libellé étroit, ou écartée | C8: Avant le dépôt
A9: 5 | B9: Montant et forme de la redevance de licence, avec les comparables | C9: Avant la licence
A10: 6 | B10: Président de l'éditrice et directeur de la publication : MIKA, ou un tiers résident français | C10: Avant la constitution de l'éditrice
A11: 7 | B11: Composition du jury du palmarès « Les Étoiles de l'assurance vie » | C11: Avant la première édition
A12: 8 | B12: Régime de TVA de la redevance : taux normal, ou franchise en base | C12: Avant la première facture

Sheet Legende
A1: Légende et mode d'emploi
A2: Classeur de pilotage du dossier LA VIE FINANCIÈRE — 20 août 2026
A4: Code couleur
A5: Texte bleu — cellule de saisie ou hypothèse : vous pouvez la modifier
A6: Texte noir — cellule calculée par une formule : ne pas écraser
A7: Texte vert — renvoi vers un autre onglet du classeur
A8: Fond jaune — cellule à remplir par vous
A9: Fond doré — total ou résultat clé
A11: Où saisir
A12: Onglet Plan d'action — colonne Statut : liste déroulante À faire / En cours / Fait / Sans objet. L'avancement se calcule tout seul en bas.
A13: Onglet Depots — cellules B4 et B5 : barème INPI. Colonne Nb de classes : le coût se recalcule.
A14: Onglet Domaines — cellule B4 : coût annuel unitaire. Colonne Action : « À réserver » déclenche le comptage dans le total.
... A18: Exemple de ligne remplie, onglet A trancher
A19: # | B19: Point | C19: Échéance | D19: Décision | E19: Date
A20: 1 | B20: Détention : seul, ou 50/50 avec Jonathan | C20: Avant le dépôt | D20: Détention seule, Jonathan informé | E20: 22/08/2026
A22: Sources et documents du dossier
A23: DOSSIER-la-vie-financiere.md — le constat de disponibilité, les domaines, la décision UDRP OMPI D2010-0529
A24: note-deontologie-structure.md — art. 22 du code de déontologie, droit de la presse, options de détention
A25: note-arret-schema.md — schéma arrêté, jurisprudence Watomet (Cass. 1re civ., 14 mai 2009, n° 08-13.422)
A26: note-editrice-et-licence.md — l'éditrice, la licence, les quatre questions sur MIKA
A27: checklist-acquisition-nom-propre.md — la marche à suivre, dont ce classeur est la version de pilotage
A28: scripts/check-domaines.py — l'outil qui a établi la disponibilité des domaines
